{
  "generatedAt": "2026-05-14T04:08:43.701Z",
  "source": "외부 뉴스 및 NIPA 공지사항",
  "categories": {
    "press": [
      {
        "title": "폴라리스AI, 국산 AI 반도체 생태계 확장…온디바이스·로봇 적용 전략 제시",
        "href": "https://news.google.com/rss/articles/CBMiakFVX3lxTE9sTVA0WUM1eGFiaDVVNXpKQ2cyem5OamVrb19mZlVIMXNvZjlhMVk3eUotSzdKSDFqcnhkSy0ySlMzUkxmTHJfYlo5T0hTUHRiYVBkVjROTzZHTFdNOUFhZWxNR05uQkpLU2c?oc=5",
        "publishedAt": "2026-05-14",
        "source": "파이낸스스코프",
        "priority": 11
      },
      {
        "title": "오케스트로, 국산 AI 반도체 생태계 키운다…112억원 R&D 사업 수행",
        "href": "https://news.google.com/rss/articles/CBMiVkFVX3lxTE4xZnlUX0FIMTVwUnVreG05NWhscHRzMG9lUmRQUFlzcXBXX00zNGhqU3ByNlNYVUcyRjNTSzQxakJVSWJNSFpENnRNd1ZqaWJJZUlMV2p3?oc=5",
        "publishedAt": "2026-05-08",
        "source": "지디넷코리아",
        "priority": 9
      }
    ],
    "notice": [
      {
        "title": "2026년 AI 기반 엔드프로덕트 상용화 지원사업 Type2 신규과제 선정평가 결과 안내",
        "href": "https://www.nipa.kr/home/2-1/16760",
        "publishedAt": "2026-05-07",
        "source": "공지사항"
      },
      {
        "title": "2026년 온디바이스 AI 서비스 실증·확산 사업 신규과제 모집공고 관련 제출서류 양식 수정 안내",
        "href": "https://www.nipa.kr/home/2-1/16729",
        "publishedAt": "2026-04-20",
        "source": "공지사항"
      }
    ]
  },
  "errors": []
}